coroexecutor.py
coroexecutor-2022.8.1.dist-info/LICENSE
coroexecutor-2022.8.1.dist-info/METADATA
coroexecutor-2022.8.1.dist-info/WHEEL
coroexecutor-2022.8.1.dist-info/top_level.txt
coroexecutor-2022.8.1.dist-info/RECORD
